{"NJACOBIANNZ":3231,"OBJCURVATURE":"linear","NNLBINVARS":0,"NLAGHESSIANNZ":3,"MINJACCOEF":0.017453071,"OBJTYPE":"linear","NGENNLCONS":0,"LIBRARY":"minlplib2","MAXJACCOEFEQU":"e94","NSOS2":0,"NOBJNLNZ":0,"OBJBOUND":1.046487647,"MINOBJCOEF":1,"MAXSCALE":8,"MAXJACCOEFVAR":"x15","LAGHESSIANAVGBLOCKSIZE":1.0,"NNLINTVARS":0,"NLINCONS":306,"LAGHESSIANMINBLOCKSIZE":1,"NCONS":307,"NAME":"fdesign10","CONSCURVATURE":"indefinite","NINTVARS":0,"NQUADCONS":1,"MAXOBJCOEFVAR":"objvar","SOURCE":"http://www.gamsworld.org/minlp/minlplib2/html/","MAXSCALEVAR":"x15","MAXSCALEEQU":"e94","NSIGNOMCONS":0,"MINSCALEVAR":"x1","MAXOBJCOEF":1,"MINSCALE":5.879542597e-15,"MINJACCOEFVAR":"x2","NLAGHESSIANDIAGNZ":3,"NOBJNZ":1,"NSOS1":0,"NLOPERANDS":null,"MINSCALEEQU":"e246","NVARS":15,"LAGHESSIANMAXBLOCKSIZE":1,"NPOLYNOMCONS":0,"NNLSEMI":0,"NSEMI":0,"MAXJACCOEF":4,"OBJSENSE":"min","MINJACCOEFEQU":"e54","NBINVARS":0,"NNLVARS":3,"NJACOBIANNLNZ":3,"MINOBJCOEFVAR":"objvar","NLAGHESSIANBLOCKS":3}