{"NJACOBIANNZ":197,"OBJCURVATURE":"linear","NNLBINVARS":0,"NLAGHESSIANNZ":40,"MINJACCOEF":0.1,"OBJTYPE":"linear","NGENNLCONS":0,"LIBRARY":"minlplib2","MAXJACCOEFEQU":"e22","NSOS2":0,"NOBJNLNZ":0,"OBJBOUND":-549.8030503,"MINOBJCOEF":3,"MAXSCALE":4.5,"MAXJACCOEFVAR":"x21","LAGHESSIANAVGBLOCKSIZE":6.5,"NNLINTVARS":0,"NLINCONS":29,"LAGHESSIANMINBLOCKSIZE":6,"NCONS":49,"NAME":"pooling_adhya1pq","CONSCURVATURE":"indefinite","NINTVARS":0,"NQUADCONS":20,"MAXOBJCOEFVAR":"x24","SOURCE":"http://www.gamsworld.org/minlp/minlplib2/html/","MAXSCALEVAR":"x21","MAXSCALEEQU":"e22","NSIGNOMCONS":0,"MINSCALEVAR":"x16","MAXOBJCOEF":23,"MINSCALE":0.5,"MINJACCOEFVAR":"x32","NLAGHESSIANDIAGNZ":0,"NOBJNZ":19,"NSOS1":0,"NLOPERANDS":null,"MINSCALEEQU":"e19","NVARS":33,"LAGHESSIANMAXBLOCKSIZE":7,"NPOLYNOMCONS":0,"NNLSEMI":0,"NSEMI":0,"MAXJACCOEF":4.5,"OBJSENSE":"min","MINJACCOEFEQU":"e20","NBINVARS":0,"NNLVARS":13,"NJACOBIANNLNZ":40,"MINOBJCOEFVAR":"x18","NLAGHESSIANBLOCKS":2}